{"original alignment (0-2000ms after trial start)": {"_type": "html-file", "sha256": "706d5647d0437921229d885b2e8a355e1ff2a38b99c53fc8a6110300dcb6bf89", "size": 252953, "path": "media/html/original alignment (0-2000ms after trial start)_0_706d5647d0437921229d.html"}, "_timestamp": 1669648833.4900568, "_runtime": 72.05324673652649, "_step": 5, "movement alignment (0-2000ms after movement onset)": {"_type": "html-file", "sha256": "85cbeddf06e135142a724e99c08f03b6c6d78865529fab9e1125851942591fdc", "size": 245122, "path": "media/html/movement alignment (0-2000ms after movement onset)_1_85cbeddf06e135142a72.html"}, "movement alignment (0-1250ms after movement onset)": {"_type": "html-file", "sha256": "e9c759cc3a491c902e32c112dac814d4f7ffa60599f969aa423df714ca0540c8", "size": 160889, "path": "media/html/movement alignment (0-1250ms after movement onset)_5_e9c759cc3a491c902e32.html"}, "movement alignment (-700-1250ms after movement onset)": {"_type": "html-file", "sha256": "bcd1c3a7afd149b3a5c378a838772bff09ba526d48ad0f6f256ac2da0b621a82", "size": 244597, "path": "media/html/movement alignment (-700-1250ms after movement onset)_3_bcd1c3a7afd149b3a5c3.html"}, "movement alignment (-700-0ms after movement onset)": {"_type": "html-file", "sha256": "0e4a62b8456f0337c36324d6f31e77b52be77cd697dc5595f207b12378a5d2c8", "size": 94214, "path": "media/html/movement alignment (-700-0ms after movement onset)_4_0e4a62b8456f0337c363.html"}}